yardang/__init__.py
yardang/build.py
yardang/cli.py
yardang/conf.py.j2
yardang/custom.css
yardang/custom.js
yardang/utils.py
yardang/tests/test_all.py
yardang-0.4.0.dist-info/METADATA
yardang-0.4.0.dist-info/WHEEL
yardang-0.4.0.dist-info/entry_points.txt
yardang-0.4.0.dist-info/licenses/LICENSE
yardang-0.4.0.dist-info/RECORD
