Metadata-Version: 2.4
Name: yardang
Version: 0.4.0
Summary: Easily generate sphinx documentation
Project-URL: Repository, https://github.com/python-project-templates/yardang
Project-URL: Homepage, https://github.com/python-project-templates/yardang
Author-email: the yardang authors <t.paine154@gmail.com>
License: Apache-2.0
License-File: LICENSE
Classifier: Development Status :: 3 - Alpha
Classifier: Programming Language :: Python
Classifier: Programming Language :: Python :: 3
Classifier: Programming Language :: Python :: 3.10
Classifier: Programming Language :: Python :: 3.11
Classifier: Programming Language :: Python :: 3.12
Classifier: Programming Language :: Python :: 3.13
Classifier: Programming Language :: Python :: 3.14
Classifier: Programming Language :: Python :: Implementation :: CPython
Classifier: Programming Language :: Python :: Implementation :: PyPy
Requires-Python: >=3.10
Requires-Dist: autodoc-pydantic
Requires-Dist: furo
Requires-Dist: myst-nb
Requires-Dist: packaging
Requires-Dist: rich
Requires-Dist: sphinx-autoapi
Requires-Dist: sphinx-copybutton
Requires-Dist: sphinx-design
Requires-Dist: sphinx-reredirects
Requires-Dist: sphinx<9,>=7.2.6
Requires-Dist: sphinxcontrib-mermaid<2.1,>=2.0.0rc0
Requires-Dist: toml
Requires-Dist: typer
Provides-Extra: develop
Requires-Dist: build; extra == 'develop'
Requires-Dist: bump-my-version; extra == 'develop'
Requires-Dist: check-manifest; extra == 'develop'
Requires-Dist: codespell<2.5,>=2.4; extra == 'develop'
Requires-Dist: hatchling; extra == 'develop'
Requires-Dist: mdformat-tables>=1; extra == 'develop'
Requires-Dist: mdformat<1.1,>=0.7.22; extra == 'develop'
Requires-Dist: pytest; extra == 'develop'
Requires-Dist: pytest-cov; extra == 'develop'
Requires-Dist: ruff<0.15,>=0.9; extra == 'develop'
Requires-Dist: twine; extra == 'develop'
Requires-Dist: uv; extra == 'develop'
Requires-Dist: wheel; extra == 'develop'
